amdl/__init__.py
amdl-0.1.1.dist-info/METADATA
amdl-0.1.1.dist-info/WHEEL
amdl-0.1.1.dist-info/top_level.txt
amdl-0.1.1.dist-info/RECORD
