Metadata-Version: 2.4
Name: amdl
Version: 0.1.1
Summary: This allows you to load modules in an elegant way.
Home-page: https://github.com/zZarby/amdl
Author: Zarby
Author-email: ZarbyTheOne@proton.me
Classifier: Programming Language :: Python :: 3
Classifier: License :: OSI Approved :: MIT License
Classifier: Operating System :: OS Independent
Requires-Python: >=3.6
Dynamic: author
Dynamic: author-email
Dynamic: classifier
Dynamic: description
Dynamic: description-content-type
Dynamic: home-page
Dynamic: requires-python
Dynamic: summary
